LICENSE
README.md
setup.py
st_undetected_chromedriver.egg-info/PKG-INFO
st_undetected_chromedriver.egg-info/SOURCES.txt
st_undetected_chromedriver.egg-info/dependency_links.txt
st_undetected_chromedriver.egg-info/requires.txt
st_undetected_chromedriver.egg-info/top_level.txt
undetected_chromedriver/__init__.py
undetected_chromedriver/cdp.py
undetected_chromedriver/dprocess.py
undetected_chromedriver/options.py
undetected_chromedriver/patcher.py
undetected_chromedriver/reactor.py
undetected_chromedriver/v2.py