Metadata-Version: 2.1
Name: st-undetected-chromedriver
Version: 3.0.8
Summary:     selenium.webdriver.Chrome replacement wiht compatiblity for Brave, and other Chromium baed browsers.     not triggered by CloudFlare/Imperva/hCaptcha and such.          NOTE: results may vary due to many factors. No guarantees are given, except for ongoing efforts in understanding detection algorithms.     
Home-page: https://github.com/baddiamond/undetected-chromedriver
Author: UltrafunkAmsterdam/baddiamond-support
Author-email: info@blackhat-security.nl
License: GPL-3.0
Platform: UNKNOWN
Classifier: License :: OSI Approved :: GNU General Public License v3 (GPLv3)
Classifier: Programming Language :: Python :: 3
Classifier: Programming Language :: Python :: 3.7
Classifier: Programming Language :: Python :: 3.8
Classifier: Programming Language :: Python :: 3.9
Classifier: Programming Language :: Python :: 3.10
License-File: LICENSE
